binney/__about__.py
binney/__init__.py
binney/utils.py
binney/data/__init__.py
binney/data/data.py
binney/data/splines.py
binney/model/__init__.py
binney/model/model.py
binney/run/__init__.py
binney/run/bootstrap.py
binney/run/run.py
binney/solvers/__init__.py
binney/solvers/hierarchical_solver.py
binney/solvers/solver.py
binney-0.0.4.dist-info/LICENSE
binney-0.0.4.dist-info/METADATA
binney-0.0.4.dist-info/WHEEL
binney-0.0.4.dist-info/top_level.txt
binney-0.0.4.dist-info/RECORD
